ptpy/__init__.py
ptpy/ptp.py
ptpy/util.py
ptpy/extensions/__init__.py
ptpy/extensions/canon.py
ptpy/extensions/microsoft.py
ptpy/extensions/nikon.py
ptpy/extensions/parrot.py
ptpy/transports/__init__.py
ptpy/transports/ip.py
ptpy/transports/usb.py
ptpy-0.3.2.dist-info/DESCRIPTION.rst
ptpy-0.3.2.dist-info/METADATA
ptpy-0.3.2.dist-info/RECORD
ptpy-0.3.2.dist-info/WHEEL
ptpy-0.3.2.dist-info/metadata.json
ptpy-0.3.2.dist-info/top_level.txt
tests/hardware/__init__.py
tests/hardware/conftest.py
tests/hardware/test_camera.py
tests/hardware/test_captures.py
tests/hardware/test_compliance.py
tests/hardware/test_properties_get_set_reset.py
tests/hardware/parrot/__init__.py
tests/hardware/parrot/sequoia/__init__.py
tests/hardware/parrot/sequoia/test_enable_capture.py
tests/hardware/parrot/sequoia/test_operation_values.py
tests/hardware/parrot/sequoia/test_sequoia.py
