Metadata-Version: 2.0
Name: ptpy
Version: 0.3.2
Summary: A pure Python implementation of Picture Transfer Protocol.
Home-page: https://github.com/Parrot-Developers/sequoia-ptpy
Author: Luis Mario Domenzain
Author-email: ld@airinov.fr
License: BSD-3-Clause
Keywords: ptp mtp usb ip ptpip ptpusb parrot canon nikon microsoft
Platform: UNKNOWN
Classifier: Development Status :: 3 - Alpha
Classifier: Intended Audience :: Developers
Classifier: Intended Audience :: Education
Classifier: Intended Audience :: End Users/Desktop
Classifier: Intended Audience :: Other Audience
Classifier: Intended Audience :: Science/Research
Classifier: License :: OSI Approved :: BSD License
Classifier: Operating System :: OS Independent
Classifier: Programming Language :: Python
Classifier: Topic :: Home Automation
Classifier: Topic :: Multimedia
Classifier: Topic :: Multimedia :: Graphics
Classifier: Topic :: Multimedia :: Graphics :: Capture
Classifier: Topic :: Multimedia :: Graphics :: Capture :: Digital Camera
Classifier: Topic :: Scientific/Engineering
Classifier: Topic :: Software Development :: Libraries
Classifier: Topic :: System :: Filesystems
Classifier: Topic :: System :: Hardware
Classifier: Topic :: System :: Hardware :: Hardware Drivers
Requires-Dist: construct (==2.8.8)
Requires-Dist: hexdump (>=3.3)
Requires-Dist: python-dateutil (>=1.5)
Requires-Dist: pyusb (>=1.0.0rc1)
Requires-Dist: rainbow-logging-handler (>=2.2.2)
Requires-Dist: six (>=1.10.0)
